audit/__init__.py
audit/app/.streamlit/config.toml
audit/app/APP.py
audit/app/__init__.py
audit/app/launcher.py
audit/app/util/__init__.py
audit/app/util/commons/__init__.py
audit/app/util/commons/checks.py
audit/app/util/commons/data_preprocessing.py
audit/app/util/commons/utils.py
audit/app/util/constants/__init__.py
audit/app/util/constants/descriptions.py
audit/app/util/constants/features.py
audit/app/util/constants/metrics.py
audit/app/util/constants/sidebars.py
audit/app/util/images/AUDIT.png
audit/app/util/images/AUDIT_DM.png
audit/app/util/images/AUDIT_DM_transparent.png
audit/app/util/images/AUDIT_big.jpeg
audit/app/util/images/AUDIT_medium.jpeg
audit/app/util/images/AUDIT_transparent.png
audit/app/util/images/artorg_logo.gif
audit/app/util/images/audit_schema.png
audit/app/util/images/audit_workflow_compressed.png
audit/app/util/images/uniovi_logo.png
audit/app/util/pages/__init__.py
audit/app/util/pages/base_page.py
audit/app/util/pages/home_page.py
audit/app/util/pages/longitudinal.py
audit/app/util/pages/multi_model_performance.py
audit/app/util/pages/multivariate_feature.py
audit/app/util/pages/pairwise_model_performance.py
audit/app/util/pages/segmentation_error_matrix.py
audit/app/util/pages/single_model_performance.py
audit/app/util/pages/subject_exploration.py
audit/app/util/pages/univariate_feature.py
audit/cli.py
audit/configs/app.yml
audit/configs/feature_extraction.yml
audit/configs/itk_labels.txt
audit/configs/metric_extraction.yml
audit/feature_extraction.py
audit/features/__init__.py
audit/features/main.py
audit/features/spatial.py
audit/features/statistical.py
audit/features/texture.py
audit/features/tumor.py
audit/metric_extraction.py
audit/metrics/__init__.py
audit/metrics/commons.py
audit/metrics/error_matrix.py
audit/metrics/main.py
audit/metrics/segmentation_metrics.py
audit/metrics/statistical_tests.py
audit/utils/__init__.py
audit/utils/commons/__init__.py
audit/utils/commons/file_manager.py
audit/utils/commons/strings.py
auditapp-0.1.1.dist-info/LICENSE.md
auditapp-0.1.1.dist-info/METADATA
auditapp-0.1.1.dist-info/WHEEL
auditapp-0.1.1.dist-info/entry_points.txt
auditapp-0.1.1.dist-info/RECORD
