Metadata-Version: 2.1
Name: auditapp
Version: 0.1.1
Summary: AUDIT, Analysis & evalUation Dashboard of artIficial inTelligence
Home-page: https://github.com/caumente/AUDIT
License: Apache-2.0
Keywords: medical image analysis,deep learning,mri,model evaluation,dashboard
Author: Carlos Aumente Maestro
Author-email: carlosaumente@gmail.com
Requires-Python: >=3.10,<4.0
Classifier: Development Status :: 4 - Beta
Classifier: Environment :: Console
Classifier: Intended Audience :: Developers
Classifier: Intended Audience :: Science/Research
Classifier: License :: OSI Approved :: Apache Software License
Classifier: Natural Language :: English
Classifier: Programming Language :: Python :: 3
Classifier: Programming Language :: Python :: 3.10
Classifier: Programming Language :: Python :: 3.11
Classifier: Programming Language :: Python :: 3.12
Classifier: Programming Language :: Python :: 3.13
Classifier: Programming Language :: Python :: 3.6
Classifier: Topic :: Scientific/Engineering
Classifier: Topic :: Scientific/Engineering :: Artificial Intelligence
Classifier: Topic :: Scientific/Engineering :: Image Processing
Classifier: Topic :: Scientific/Engineering :: Medical Science Apps.
Classifier: Topic :: Software Development :: Libraries :: Python Modules
Requires-Dist: click (==8.0.0)
Requires-Dist: colorama (==0.4.6)
Requires-Dist: kaleido (==0.2.1)
Requires-Dist: loguru (==0.7.2)
Requires-Dist: matplotlib (==3.10.0)
Requires-Dist: numpy (==2.2.1)
Requires-Dist: pandas (==2.2.3)
Requires-Dist: pillow (==10.4.0)
Requires-Dist: plotly (==5.22.0)
Requires-Dist: pymia (==0.3.2)
Requires-Dist: pyyaml (==6.0.2)
Requires-Dist: scikit-image (==0.25.0)
Requires-Dist: scipy (==1.15.0)
Requires-Dist: simpleitk (==2.3.1)
Requires-Dist: st-theme (==1.2.3)
Requires-Dist: statsmodels (==0.14.0)
Requires-Dist: stqdm (==0.0.5)
Requires-Dist: streamlit (==1.41.1)
Requires-Dist: streamlit-plotly-events (==0.0.6)
Requires-Dist: tqdm (==4.64.0)
Project-URL: Documentation, https://caumente.github.io/AUDIT/
Project-URL: Repository, https://github.com/caumente/AUDIT
